{"Answers":[{"QuestionName":"Baku is capital of","UserAnswer":"B","Correct":"A"},{"QuestionName":"Azerbaijan border with","UserAnswer":"B","Correct":"D"},{"QuestionName":"Which desert is located in the southern hemisphere? ","UserAnswer":"B","Correct":"B"},{"QuestionName":"Which island is the largest in the world? ","UserAnswer":"B","Correct":"D"},{"QuestionName":"The capital of Italy? ","UserAnswer":"B","Correct":"A"},{"QuestionName":"How many ocheans on planet earth? ","UserAnswer":"B","Correct":"C"},{"QuestionName":" How many countries exist ? ","UserAnswer":"B","Correct":"C"},{"QuestionName":"The population in Azerbaijan ? ","UserAnswer":"B","Correct":"B"},{"QuestionName":" Which country is the northernmost? ? ","UserAnswer":"B","Correct":"B"},{"QuestionName":" What continent is Ethiopia on ? ","UserAnswer":"B","Correct":"D"},{"QuestionName":" Who was America discovered by? ? ","UserAnswer":"B","Correct":"C"},{"QuestionName":" Which country has the largest population ? ","UserAnswer":"B","Correct":"B"},{"QuestionName":" How many states are there in the USA? ","UserAnswer":"B","Correct":"D"},{"QuestionName":" What is the coldest place on Earth?? ","UserAnswer":"B","Correct":"C"}],"PointCount":4}
